synecdoche/__init__.py
synecdoche/_version.py
synecdoche/experimental.py
synecdoche/hyper.py
synecdoche-0.0.5.dist-info/LICENSE
synecdoche-0.0.5.dist-info/METADATA
synecdoche-0.0.5.dist-info/WHEEL
synecdoche-0.0.5.dist-info/top_level.txt
synecdoche-0.0.5.dist-info/RECORD
