Metadata-Version: 2.1
Name: synecdoche
Version: 0.0.5
Summary: Synecdoche: Hypernetworks for Haiku in JAX
Home-page: https://github.com/kmheckel/synecdoche
Author: Kade Heckel
Author-email: example@email.com
License: MIT
Classifier: Intended Audience :: Developers
Classifier: License :: OSI Approved :: MIT License
Classifier: Programming Language :: Python
Classifier: Programming Language :: Python :: 3
Classifier: Programming Language :: Python :: 3.8
Classifier: Programming Language :: Python :: 3.9
Classifier: Programming Language :: Python :: 3.10
Classifier: Operating System :: OS Independent
License-File: LICENSE
Requires-Dist: jax (>=0.3.0)
Requires-Dist: jaxlib (>=0.3.0)
Requires-Dist: dm-haiku
